law_history_mcp/__init__.py
law_history_mcp/cli.py
law_history_mcp/server.py
taiwan_law_history_mcp-0.1.3.dist-info/METADATA
taiwan_law_history_mcp-0.1.3.dist-info/WHEEL
taiwan_law_history_mcp-0.1.3.dist-info/entry_points.txt
taiwan_law_history_mcp-0.1.3.dist-info/licenses/LICENSE
taiwan_law_history_mcp-0.1.3.dist-info/RECORD
