Metadata-Version: 2.4
Name: taiwan-law-history-mcp
Version: 0.1.3
Summary: Model Context Protocol server for Taiwan law history and article scraping from Legislative Yuan database
Project-URL: Homepage, https://github.com/yourusername/taiwan-law-history-mcp
Project-URL: Repository, https://github.com/yourusername/taiwan-law-history-mcp
Project-URL: Issues, https://github.com/yourusername/taiwan-law-history-mcp/issues
Project-URL: Documentation, https://github.com/yourusername/taiwan-law-history-mcp#readme
Author-email: Taiwan Law MCP <noreply@example.com>
License: MIT
License-File: LICENSE
Keywords: law,legal,legislative-yuan,mcp,model-context-protocol,scraping,taiwan
Classifier: Development Status :: 4 - Beta
Classifier: Intended Audience :: Developers
Classifier: Intended Audience :: Legal Industry
Classifier: License :: OSI Approved :: MIT License
Classifier: Programming Language :: Python :: 3
Classifier: Programming Language :: Python :: 3.10
Classifier: Programming Language :: Python :: 3.11
Classifier: Programming Language :: Python :: 3.12
Classifier: Topic :: Internet :: WWW/HTTP :: Dynamic Content
Classifier: Topic :: Software Development :: Libraries :: Python Modules
Classifier: Topic :: Text Processing :: Markup :: HTML
Requires-Python: >=3.10
Requires-Dist: beautifulsoup4>=4.12.0
Requires-Dist: html5lib>=1.1
Requires-Dist: lxml>=4.9.0
Requires-Dist: mcp>=1.0.0
Requires-Dist: requests>=2.31.0
